{"version": 0.6, "generator": "Overpass API 0.7.62.11 87bfad18", "osm3s": {"timestamp_osm_base": "2026-05-19T03:45:44Z", "copyright": "The data included in this document is from www.openstreetmap.org. The data is made available under ODbL."}, "elements": [{"type": "node", "id": 2760645643, "lat": 31.5609914, "lon": 119.269235, "tags": {"addr:city": "\u6ea7\u9633\u5e02", "addr:postcode": "21351", "addr:street": "\u7af9\u7ba6\u9547", "addr:village": "\u5357\u65fa\u6751", "name": "\u74e6\u5c4b\u5c71", "name:en": "Wawushan Railway Station", "operator": "\u5357\u4eac\u7ad9", "railway": "station", "wikidata": "Q17061591", "wikipedia": "zh:\u74e6\u5c4b\u5c71\u7ad9"}}, {"type": "node", "id": 10120263981, "lat": 31.6972997, "lon": 119.5389768, "tags": {"name": "\u91d1\u575b", "public_transport": "station", "railway": "station", "train": "yes"}}]}